django_seo_js/__init__.py
django_seo_js/helpers.py
django_seo_js/settings.py
django_seo_js/backends/__init__.py
django_seo_js/backends/base.py
django_seo_js/backends/prerender.py
django_seo_js/backends/test.py
django_seo_js/middleware/__init__.py
django_seo_js/middleware/escaped_fragment.py
django_seo_js/middleware/hashbang.py
django_seo_js/middleware/useragent.py
django_seo_js/templatetags/__init__.py
django_seo_js/templatetags/django_seo_js.py
django_seo_js/tests/__init__.py
django_seo_js/tests/test_helpers.py
django_seo_js/tests/test_middlewares.py
django_seo_js/tests/test_pep8.py
django_seo_js/tests/test_templatetags.py
django_seo_js/tests/utils.py
django_seo_js/tests/backends/__init__.py
django_seo_js/tests/backends/test_base.py
django_seo_js/tests/backends/test_prerender_hosted.py
django_seo_js/tests/backends/test_prerender_io.py
django_seo_js-0.4.1.dist-info/AUTHORS
django_seo_js-0.4.1.dist-info/LICENSE
django_seo_js-0.4.1.dist-info/METADATA
django_seo_js-0.4.1.dist-info/WHEEL
django_seo_js-0.4.1.dist-info/top_level.txt
django_seo_js-0.4.1.dist-info/RECORD
