Metadata-Version: 2.1
Name: django-seo-js
Version: 0.4.1
Summary: SEO support for angular, backbone, ember, famo.us, and other SPA apps built with django.
Home-page: https://github.com/skoczen/django-seo-js
Author: Steven Skoczen
Author-email: steven@greenkahuna.com
Keywords: seo,django,ajax,angular,backbone,ember,famous,google,bing,yahoo
Classifier: Programming Language :: Python
Classifier: License :: OSI Approved :: BSD License
Classifier: Operating System :: OS Independent
Classifier: Development Status :: 4 - Beta
Classifier: Environment :: Web Environment
Classifier: Intended Audience :: Developers
Classifier: Topic :: Internet :: WWW/HTTP
Classifier: Topic :: Software Development :: Libraries :: Python Modules
License-File: LICENSE
License-File: AUTHORS
Requires-Dist: requests
Requires-Dist: Django
